[{"heightInM":1.5,"weightInKg":50,"username":null},{"heightInM":1.6,"weightInKg":60,"username":null},{"heightInM":1.7,"weightInKg":70,"username":null},{"heightInM":1.8,"weightInKg":80,"username":null},{"heightInM":1.5,"weightInKg":50,"username":null},{"heightInM":1.6,"weightInKg":60,"username":null},{"heightInM":1.7,"weightInKg":70,"username":null},{"heightInM":1.8,"weightInKg":80,"username":null},{"heightInM":1.58,"weightInKg":49,"username":null},{"heightInM":333,"weightInKg":555,"username":null},{"heightInM":1.5,"weightInKg":50,"username":"User1"},{"heightInM":1.6,"weightInKg":60,"username":"User2"},{"heightInM":1.7,"weightInKg":70,"username":"User3"},{"heightInM":1.8,"weightInKg":80,"username":"User4"},{"heightInM":666,"weightInKg":888,"username":null},{"heightInM":1.5,"weightInKg":50,"username":"User1"},{"heightInM":1.6,"weightInKg":60,"username":"User2"},{"heightInM":1.7,"weightInKg":70,"username":"User3"},{"heightInM":1.8,"weightInKg":80,"username":"User4"},{"heightInM":1.5,"weightInKg":50,"username":"User1"},{"heightInM":1.6,"weightInKg":60,"username":"User2"},{"heightInM":1.7,"weightInKg":70,"username":"User3"},{"heightInM":1.8,"weightInKg":80,"username":"User4"},{"heightInM":1.5,"weightInKg":50,"username":"User1"},{"heightInM":1.6,"weightInKg":60,"username":"User2"},{"heightInM":1.7,"weightInKg":70,"username":"User3"},{"heightInM":1.8,"weightInKg":80,"username":"User4"},{"heightInM":0,"weightInKg":0,"username":null},{"heightInM":0,"weightInKg":0,"username":null},{"heightInM":1.5,"weightInKg":50,"username":"User1"},{"heightInM":1.6,"weightInKg":60,"username":"User2"},{"heightInM":1.7,"weightInKg":70,"username":"User3"},{"heightInM":1.8,"weightInKg":80,"username":"User4"},{"heightInM":0,"weightInKg":0,"username":null},{"heightInM":1.5,"weightInKg":50,"username":"User1"},{"heightInM":1.6,"weightInKg":60,"username":"User2"},{"heightInM":1.7,"weightInKg":70,"username":"User3"},{"heightInM":1.8,"weightInKg":80,"username":"User4"},{"heightInM":0,"weightInKg":0,"username":null},{"heightInM":0,"weightInKg":0,"username":null}]